tk_sql_tls/__init__.py
tk_sql_tls/dashboard.py
tk_sql_tls/db.py
tk_sql_tls/main.py
tk_sql_tls/test.txt
tk_sql_tls/tz.txt
tk_sql_tls-0.1.0.dist-info/licenses/LICENSE
tk_sql_tls-0.1.0.dist-info/METADATA
tk_sql_tls-0.1.0.dist-info/WHEEL
tk_sql_tls-0.1.0.dist-info/entry_points.txt
tk_sql_tls-0.1.0.dist-info/top_level.txt
tk_sql_tls-0.1.0.dist-info/RECORD
