Metadata-Version: 2.4
Name: tk_sql_tls
Version: 0.1.0
Summary: Библиотека для работы с SQL, Tkinter и временными зонами
Author-email: Твое Имя <your.email@example.com>
Maintainer-email: Твое Имя <your.email@example.com>
License: MIT License
Classifier: Programming Language :: Python :: 3
Classifier: Programming Language :: Python :: 3.7
Classifier: Programming Language :: Python :: 3.8
Classifier: Programming Language :: Python :: 3.9
Classifier: Programming Language :: Python :: 3.10
Classifier: License :: OSI Approved :: MIT License
Classifier: Operating System :: OS Independent
Requires-Python: >=3.7
License-File: LICENSE
Dynamic: license-file
